{
  "module": "Бизнес",
  "exercise_id": "biz_energy_budget_01",
  "title": "Energy Budget: план без самообмана",
  "description": "Упражнение на распределение ограниченного времени и энергии по приоритетам.",
  "objective": "Научить строить реалистичный план и объяснять ограничения бизнесу.",
  "difficulty": "medium",
  "estimated_minutes": 8,
  "skills": [
    "приоритизация",
    "планирование",
    "управление ожиданиями"
  ],
  "ybt_weights": {
    "self": 0.2,
    "business": 0.6,
    "team": 0.2
  },
  "engine": {
    "type": "scripted",
    "selection_mode": "single",
    "show_consequence_immediately": true,
    "show_step_feedback": true,
    "shuffle_options": false,
    "pass_threshold": 70
  },
  "steps": [
    {
      "step_id": "step_1",
      "scene_title": "План недели",
      "text": "У вас 18 задач и 40 рабочих часов. С чего начать Energy Budget?",
      "correct_option_id": "a",
      "feedback": {
        "correct": "Energy Budget начинается не со списка дел, а с емкости и приоритетов.",
        "incorrect": "Сильный ответ сначала ограничивает поле, а потом распределяет ресурс."
      },
      "options": [
        {
          "id": "a",
          "text": "Разделить задачи на must / should / could и оценить энергозатратность ключевых блоков",
          "correct": true,
          "consequence": "Вы связываете приоритеты бизнеса с реальной емкостью недели.",
          "score": 10,
          "ybt_delta": {
            "self": 1,
            "business": 2,
            "team": 0
          },
          "tags": [
            "приоритет",
            "емкость"
          ]
        },
        {
          "id": "b",
          "text": "Пытаться уместить все, а потом разбираться по ходу",
          "correct": false,
          "consequence": "Такой подход почти гарантирует хаос и перегруз.",
          "score": 0,
          "ybt_delta": {
            "self": -1,
            "business": -1,
            "team": 0
          },
          "tags": [
            "хаос"
          ]
        },
        {
          "id": "c",
          "text": "Сначала делать самое приятное",
          "correct": false,
          "consequence": "Это может дать быстрый дофамин, но не управляет результатом.",
          "score": 1,
          "ybt_delta": {
            "self": 0,
            "business": -1,
            "team": 0
          },
          "tags": [
            "избегание"
          ]
        }
      ]
    },
    {
      "step_id": "step_2",
      "scene_title": "Фокусировка",
      "text": "Какое решение лучше для задач категории could?",
      "correct_option_id": "b",
      "feedback": {
        "correct": "Правильный бюджет — это не обещание всего, а ясная отсечка лишнего.",
        "incorrect": "Лучшие ответы делают план честным."
      },
      "options": [
        {
          "id": "a",
          "text": "Оставить в плане, вдруг успею",
          "correct": false,
          "consequence": "Иллюзия вместимости разрушает реалистичность плана.",
          "score": 0,
          "ybt_delta": {
            "self": -1,
            "business": -1,
            "team": 0
          },
          "tags": [
            "нереалистичный план"
          ]
        },
        {
          "id": "b",
          "text": "Вынести в backlog и назначить условия возврата: если освободится 4+ часа",
          "correct": true,
          "consequence": "Вы снижаете шум и сохраняете управляемость.",
          "score": 10,
          "ybt_delta": {
            "self": 1,
            "business": 2,
            "team": 0
          },
          "tags": [
            "backlog",
            "реализм"
          ]
        },
        {
          "id": "c",
          "text": "Передать все could команде без обсуждения",
          "correct": false,
          "consequence": "Вы снимаете нагрузку с себя, но не создаете осознанного распределения.",
          "score": 1,
          "ybt_delta": {
            "self": 1,
            "business": 0,
            "team": -1
          },
          "tags": [
            "сброс нагрузки"
          ]
        }
      ]
    },
    {
      "step_id": "step_3",
      "scene_title": "Коммуникация вверх",
      "text": "Руководитель спрашивает, почему вы не взяли еще 3 задачи. Что отвечаете?",
      "correct_option_id": "a",
      "feedback": {
        "correct": "В бизнес-контуре важна не жесткость, а прозрачное управление обещаниями.",
        "incorrect": "Показывайте trade-off, а не просто говорите «нет»."
      },
      "options": [
        {
          "id": "a",
          "text": "Говорю: «Сейчас в committed-плане 5 задач, еще 3 снизят качество и сроки. Могу взять их после закрытия блока А»",
          "correct": true,
          "consequence": "Вы объясняете отказ через последствия для бизнеса.",
          "score": 10,
          "ybt_delta": {
            "self": 1,
            "business": 2,
            "team": 1
          },
          "tags": [
            "управление ожиданиями"
          ]
        },
        {
          "id": "b",
          "text": "Соглашаюсь, а там посмотрим",
          "correct": false,
          "consequence": "Вы покупаете краткий комфорт ценой будущего провала.",
          "score": 0,
          "ybt_delta": {
            "self": -2,
            "business": -1,
            "team": 0
          },
          "tags": [
            "перегруз"
          ]
        },
        {
          "id": "c",
          "text": "Отвечаю резко: «Это невозможно»",
          "correct": false,
          "consequence": "Правда без конструкции ухудшает сотрудничество.",
          "score": 2,
          "ybt_delta": {
            "self": 0,
            "business": 0,
            "team": -1
          },
          "tags": [
            "резкость"
          ]
        }
      ]
    }
  ],
  "completion_feedback": "Вы отработали одну из главных управленческих привычек: план строится от емкости, а не от хотелок.",
  "retry_tips": [
    "Ищите решения, где есть честная отсечка лишнего.",
    "Лучшие ответы объясняют ограничения через последствия для результата."
  ]
}